[
	{
		"name": "utils",
		"title": "Utils",
		"type": "registry:lib",
		"description": "Kura utility helpers used by the component source.",
		"registryDependencies": [],
		"relativeUrl": "utils.json"
	},
	{
		"name": "is-mobile",
		"title": "Is Mobile",
		"type": "registry:hook",
		"description": "Kura Is Mobile hook.",
		"registryDependencies": [],
		"relativeUrl": "is-mobile.json"
	},
	{
		"name": "accordion",
		"title": "Accordion",
		"type": "registry:ui",
		"description": "Kura Accordion component source.",
		"registryDependencies": [
			"utils"
		],
		"relativeUrl": "accordion.json"
	},
	{
		"name": "alert",
		"title": "Alert",
		"type": "registry:ui",
		"description": "Kura Alert component source.",
		"registryDependencies": [
			"utils"
		],
		"relativeUrl": "alert.json"
	},
	{
		"name": "alert-dialog",
		"title": "Alert Dialog",
		"type": "registry:ui",
		"description": "Kura Alert Dialog component source.",
		"registryDependencies": [
			"button",
			"utils"
		],
		"relativeUrl": "alert-dialog.json"
	},
	{
		"name": "aspect-ratio",
		"title": "Aspect Ratio",
		"type": "registry:ui",
		"description": "Kura Aspect Ratio component source.",
		"registryDependencies": [
			"utils"
		],
		"relativeUrl": "aspect-ratio.json"
	},
	{
		"name": "avatar",
		"title": "Avatar",
		"type": "registry:ui",
		"description": "Kura Avatar component source.",
		"registryDependencies": [
			"utils"
		],
		"relativeUrl": "avatar.json"
	},
	{
		"name": "badge",
		"title": "Badge",
		"type": "registry:ui",
		"description": "Kura Badge component source.",
		"registryDependencies": [
			"utils"
		],
		"relativeUrl": "badge.json"
	},
	{
		"name": "breadcrumb",
		"title": "Breadcrumb",
		"type": "registry:ui",
		"description": "Kura Breadcrumb component source.",
		"registryDependencies": [
			"utils"
		],
		"relativeUrl": "breadcrumb.json"
	},
	{
		"name": "button",
		"title": "Button",
		"type": "registry:ui",
		"description": "Kura Button component source.",
		"registryDependencies": [
			"utils"
		],
		"relativeUrl": "button.json"
	},
	{
		"name": "button-group",
		"title": "Button Group",
		"type": "registry:ui",
		"description": "Kura Button Group component source.",
		"registryDependencies": [
			"separator",
			"utils"
		],
		"relativeUrl": "button-group.json"
	},
	{
		"name": "calendar",
		"title": "Calendar",
		"type": "registry:ui",
		"description": "Kura Calendar component source.",
		"registryDependencies": [
			"button",
			"utils"
		],
		"relativeUrl": "calendar.json"
	},
	{
		"name": "card",
		"title": "Card",
		"type": "registry:ui",
		"description": "Kura Card component source.",
		"registryDependencies": [
			"utils"
		],
		"relativeUrl": "card.json"
	},
	{
		"name": "carousel",
		"title": "Carousel",
		"type": "registry:ui",
		"description": "Kura Carousel component source.",
		"registryDependencies": [
			"button",
			"utils"
		],
		"relativeUrl": "carousel.json"
	},
	{
		"name": "chart",
		"title": "Chart",
		"type": "registry:ui",
		"description": "Kura Chart component source.",
		"registryDependencies": [
			"utils"
		],
		"relativeUrl": "chart.json"
	},
	{
		"name": "checkbox",
		"title": "Checkbox",
		"type": "registry:ui",
		"description": "Kura Checkbox component source.",
		"registryDependencies": [
			"utils"
		],
		"relativeUrl": "checkbox.json"
	},
	{
		"name": "collapsible",
		"title": "Collapsible",
		"type": "registry:ui",
		"description": "Kura Collapsible component source.",
		"registryDependencies": [
			"utils"
		],
		"relativeUrl": "collapsible.json"
	},
	{
		"name": "command",
		"title": "Command",
		"type": "registry:ui",
		"description": "Kura Command component source.",
		"registryDependencies": [
			"dialog",
			"input-group",
			"utils"
		],
		"relativeUrl": "command.json"
	},
	{
		"name": "context-menu",
		"title": "Context Menu",
		"type": "registry:ui",
		"description": "Kura Context Menu component source.",
		"registryDependencies": [
			"utils"
		],
		"relativeUrl": "context-menu.json"
	},
	{
		"name": "data-table",
		"title": "Data Table",
		"type": "registry:ui",
		"description": "Kura Data Table component source.",
		"registryDependencies": [],
		"relativeUrl": "data-table.json"
	},
	{
		"name": "dialog",
		"title": "Dialog",
		"type": "registry:ui",
		"description": "Kura Dialog component source.",
		"registryDependencies": [
			"button",
			"utils"
		],
		"relativeUrl": "dialog.json"
	},
	{
		"name": "drawer",
		"title": "Drawer",
		"type": "registry:ui",
		"description": "Kura Drawer component source.",
		"registryDependencies": [
			"utils"
		],
		"relativeUrl": "drawer.json"
	},
	{
		"name": "dropdown-menu",
		"title": "Dropdown Menu",
		"type": "registry:ui",
		"description": "Kura Dropdown Menu component source.",
		"registryDependencies": [
			"utils"
		],
		"relativeUrl": "dropdown-menu.json"
	},
	{
		"name": "empty",
		"title": "Empty",
		"type": "registry:ui",
		"description": "Kura Empty component source.",
		"registryDependencies": [
			"utils"
		],
		"relativeUrl": "empty.json"
	},
	{
		"name": "field",
		"title": "Field",
		"type": "registry:ui",
		"description": "Kura Field component source.",
		"registryDependencies": [
			"label",
			"separator",
			"utils"
		],
		"relativeUrl": "field.json"
	},
	{
		"name": "form",
		"title": "Form",
		"type": "registry:ui",
		"description": "Kura Form component source.",
		"registryDependencies": [
			"button",
			"label",
			"utils"
		],
		"relativeUrl": "form.json"
	},
	{
		"name": "hover-card",
		"title": "Hover Card",
		"type": "registry:ui",
		"description": "Kura Hover Card component source.",
		"registryDependencies": [
			"utils"
		],
		"relativeUrl": "hover-card.json"
	},
	{
		"name": "input",
		"title": "Input",
		"type": "registry:ui",
		"description": "Kura Input component source.",
		"registryDependencies": [
			"utils"
		],
		"relativeUrl": "input.json"
	},
	{
		"name": "input-group",
		"title": "Input Group",
		"type": "registry:ui",
		"description": "Kura Input Group component source.",
		"registryDependencies": [
			"button",
			"input",
			"textarea",
			"utils"
		],
		"relativeUrl": "input-group.json"
	},
	{
		"name": "input-otp",
		"title": "Input Otp",
		"type": "registry:ui",
		"description": "Kura Input Otp component source.",
		"registryDependencies": [
			"utils"
		],
		"relativeUrl": "input-otp.json"
	},
	{
		"name": "item",
		"title": "Item",
		"type": "registry:ui",
		"description": "Kura Item component source.",
		"registryDependencies": [
			"separator",
			"utils"
		],
		"relativeUrl": "item.json"
	},
	{
		"name": "kbd",
		"title": "Kbd",
		"type": "registry:ui",
		"description": "Kura Kbd component source.",
		"registryDependencies": [
			"utils"
		],
		"relativeUrl": "kbd.json"
	},
	{
		"name": "label",
		"title": "Label",
		"type": "registry:ui",
		"description": "Kura Label component source.",
		"registryDependencies": [
			"utils"
		],
		"relativeUrl": "label.json"
	},
	{
		"name": "menubar",
		"title": "Menubar",
		"type": "registry:ui",
		"description": "Kura Menubar component source.",
		"registryDependencies": [
			"utils"
		],
		"relativeUrl": "menubar.json"
	},
	{
		"name": "native-select",
		"title": "Native Select",
		"type": "registry:ui",
		"description": "Kura Native Select component source.",
		"registryDependencies": [
			"utils"
		],
		"relativeUrl": "native-select.json"
	},
	{
		"name": "navigation-menu",
		"title": "Navigation Menu",
		"type": "registry:ui",
		"description": "Kura Navigation Menu component source.",
		"registryDependencies": [
			"utils"
		],
		"relativeUrl": "navigation-menu.json"
	},
	{
		"name": "pagination",
		"title": "Pagination",
		"type": "registry:ui",
		"description": "Kura Pagination component source.",
		"registryDependencies": [
			"button",
			"utils"
		],
		"relativeUrl": "pagination.json"
	},
	{
		"name": "popover",
		"title": "Popover",
		"type": "registry:ui",
		"description": "Kura Popover component source.",
		"registryDependencies": [
			"utils"
		],
		"relativeUrl": "popover.json"
	},
	{
		"name": "progress",
		"title": "Progress",
		"type": "registry:ui",
		"description": "Kura Progress component source.",
		"registryDependencies": [
			"utils"
		],
		"relativeUrl": "progress.json"
	},
	{
		"name": "radio-group",
		"title": "Radio Group",
		"type": "registry:ui",
		"description": "Kura Radio Group component source.",
		"registryDependencies": [
			"utils"
		],
		"relativeUrl": "radio-group.json"
	},
	{
		"name": "range-calendar",
		"title": "Range Calendar",
		"type": "registry:ui",
		"description": "Kura Range Calendar component source.",
		"registryDependencies": [
			"button",
			"utils"
		],
		"relativeUrl": "range-calendar.json"
	},
	{
		"name": "resizable",
		"title": "Resizable",
		"type": "registry:ui",
		"description": "Kura Resizable component source.",
		"registryDependencies": [
			"utils"
		],
		"relativeUrl": "resizable.json"
	},
	{
		"name": "scroll-area",
		"title": "Scroll Area",
		"type": "registry:ui",
		"description": "Kura Scroll Area component source.",
		"registryDependencies": [
			"utils"
		],
		"relativeUrl": "scroll-area.json"
	},
	{
		"name": "select",
		"title": "Select",
		"type": "registry:ui",
		"description": "Kura Select component source.",
		"registryDependencies": [
			"separator",
			"utils"
		],
		"relativeUrl": "select.json"
	},
	{
		"name": "separator",
		"title": "Separator",
		"type": "registry:ui",
		"description": "Kura Separator component source.",
		"registryDependencies": [
			"utils"
		],
		"relativeUrl": "separator.json"
	},
	{
		"name": "sheet",
		"title": "Sheet",
		"type": "registry:ui",
		"description": "Kura Sheet component source.",
		"registryDependencies": [
			"button",
			"utils"
		],
		"relativeUrl": "sheet.json"
	},
	{
		"name": "sidebar",
		"title": "Sidebar",
		"type": "registry:ui",
		"description": "Kura Sidebar component source.",
		"registryDependencies": [
			"button",
			"input",
			"is-mobile",
			"separator",
			"sheet",
			"skeleton",
			"tooltip",
			"utils"
		],
		"relativeUrl": "sidebar.json"
	},
	{
		"name": "skeleton",
		"title": "Skeleton",
		"type": "registry:ui",
		"description": "Kura Skeleton component source.",
		"registryDependencies": [
			"utils"
		],
		"relativeUrl": "skeleton.json"
	},
	{
		"name": "slider",
		"title": "Slider",
		"type": "registry:ui",
		"description": "Kura Slider component source.",
		"registryDependencies": [
			"utils"
		],
		"relativeUrl": "slider.json"
	},
	{
		"name": "sonner",
		"title": "Sonner",
		"type": "registry:ui",
		"description": "Kura Sonner component source.",
		"registryDependencies": [],
		"relativeUrl": "sonner.json"
	},
	{
		"name": "spinner",
		"title": "Spinner",
		"type": "registry:ui",
		"description": "Kura Spinner component source.",
		"registryDependencies": [
			"utils"
		],
		"relativeUrl": "spinner.json"
	},
	{
		"name": "switch",
		"title": "Switch",
		"type": "registry:ui",
		"description": "Kura Switch component source.",
		"registryDependencies": [
			"utils"
		],
		"relativeUrl": "switch.json"
	},
	{
		"name": "table",
		"title": "Table",
		"type": "registry:ui",
		"description": "Kura Table component source.",
		"registryDependencies": [
			"utils"
		],
		"relativeUrl": "table.json"
	},
	{
		"name": "tabs",
		"title": "Tabs",
		"type": "registry:ui",
		"description": "Kura Tabs component source.",
		"registryDependencies": [
			"utils"
		],
		"relativeUrl": "tabs.json"
	},
	{
		"name": "textarea",
		"title": "Textarea",
		"type": "registry:ui",
		"description": "Kura Textarea component source.",
		"registryDependencies": [
			"utils"
		],
		"relativeUrl": "textarea.json"
	},
	{
		"name": "toggle",
		"title": "Toggle",
		"type": "registry:ui",
		"description": "Kura Toggle component source.",
		"registryDependencies": [
			"utils"
		],
		"relativeUrl": "toggle.json"
	},
	{
		"name": "toggle-group",
		"title": "Toggle Group",
		"type": "registry:ui",
		"description": "Kura Toggle Group component source.",
		"registryDependencies": [
			"toggle",
			"utils"
		],
		"relativeUrl": "toggle-group.json"
	},
	{
		"name": "tooltip",
		"title": "Tooltip",
		"type": "registry:ui",
		"description": "Kura Tooltip component source.",
		"registryDependencies": [
			"utils"
		],
		"relativeUrl": "tooltip.json"
	}
]